<?xml version="1.0"?>

<robot
  xmlns:xacro="http://playerstage.sourceforge.net/gazebo/xmlschema/#interface">
  
  <macro name="arm_link_0_collision_geom_marco">
    <collision>
      <origin xyz="0.0 0.0 ${0.17651*0.5+ 0.001}" rpy="0 0 0" />
      <geometry>
        <box size="${0.0475*2} ${0.038*2} 0.17651" />
      </geometry>
    </collision>
  </macro>  
  
  <macro name="arm_link_1_collision_geom_marco">
    <collision>
      <origin xyz="-0.055 ${0.651*0.5 -0.05}  0.0225" rpy="0 0 0" />
      <geometry>
        <box size="${0.09} ${0.651}  0.136" />
      </geometry>
    </collision>
  </macro>  
  
  <macro name="arm_link_2_collision_geom_marco">
    <collision>
      <origin xyz="${0.047} ${-0.5125*0.5 + 0.048} 0.0" rpy="0 0 0" />
      <geometry>
        <box size="0.073 ${0.5125} 0.086" />
      </geometry>
    </collision>
  </macro>  
  
  <macro name="arm_link_3_collision_geom_marco">
    <collision>
      <origin xyz="0.045 ${-0.208*0.5 + 0.03919} 0.0" rpy="0 0 0" />
      <geometry>
        <box size="0.07 ${0.208} 0.091" />
      </geometry>
    </collision>
  </macro>  
  
</robot>
